LICENSE.md
MANIFEST.in
README.md
pyproject.toml
setup.cfg
setup.py
src/data_loader/__init__.py
src/data_loader/data_loader.py
src/data_loader/other_extensions.py
src/dynamic_loader.egg-info/PKG-INFO
src/dynamic_loader.egg-info/SOURCES.txt
src/dynamic_loader.egg-info/dependency_links.txt
src/dynamic_loader.egg-info/top_level.txt
tests/test_data_loader.py